evergreen/__init__.py
evergreen/alias.py
evergreen/api.py
evergreen/api_requests.py
evergreen/base.py
evergreen/build.py
evergreen/cli/__init__.py
evergreen/cli/main.py
evergreen/commitqueue.py
evergreen/config.py
evergreen/distro.py
evergreen/errors/__init__.py
evergreen/errors/exceptions.py
evergreen/host.py
evergreen/manifest.py
evergreen/metrics/__init__.py
evergreen/metrics/buildmetrics.py
evergreen/metrics/versionmetrics.py
evergreen/patch.py
evergreen/performance_results.py
evergreen/project.py
evergreen/py.typed
evergreen/resource_type_permissions.py
evergreen/stats.py
evergreen/task.py
evergreen/task_annotations.py
evergreen/task_reliability.py
evergreen/tst.py
evergreen/users_for_role.py
evergreen/util.py
evergreen/version.py
evergreen_py-3.13.1.dist-info/LICENSE
evergreen_py-3.13.1.dist-info/METADATA
evergreen_py-3.13.1.dist-info/WHEEL
evergreen_py-3.13.1.dist-info/entry_points.txt
evergreen_py-3.13.1.dist-info/RECORD
