Metadata-Version: 2.3
Name: evergreen.py
Version: 3.13.1
Summary: Python client for the Evergreen API
License: Apache-2.0
Author: DevProd Services & Integrations Team
Author-email: devprod-si-team@mongodb.com
Requires-Python: >=3.9,<3.14
Classifier: License :: OSI Approved :: Apache Software License
Classifier: Programming Language :: Python :: 3
Classifier: Programming Language :: Python :: 3.9
Classifier: Programming Language :: Python :: 3.10
Classifier: Programming Language :: Python :: 3.11
Classifier: Programming Language :: Python :: 3.12
Classifier: Programming Language :: Python :: 3.13
Requires-Dist: Click (>=8,<9)
Requires-Dist: PyYAML (>=5)
Requires-Dist: packaging (>=25.0,<26.0)
Requires-Dist: pydantic (>=1)
Requires-Dist: python-dateutil (>=2)
Requires-Dist: requests (>=2)
Requires-Dist: structlog (>=19)
Project-URL: Repository, https://github.com/evergreen-ci/evergreen.py
